setup.py
lib/__init__.py
lib/get_mutations.py
lib/get_scores.py
lib/get_seq.py
lib/get_specificity.py
lib/global_vars.py
lib/io_dfs.py
lib/io_nums.py
lib/io_seqs.py
lib/io_strs.py
lib/io_sys.py
lib/make_guides.py
lib/plot_res.py
super_beditor.egg-info/PKG-INFO
super_beditor.egg-info/SOURCES.txt
super_beditor.egg-info/dependency_links.txt
super_beditor.egg-info/entry_points.txt
super_beditor.egg-info/requires.txt
super_beditor.egg-info/top_level.txt